vbp/__init__.py
vbp/example.py
vbp/run.py
vbp/data/population/WPP2017_POP_F01_1_TOTAL_POPULATION_BOTH_SEXES.xlsx
vbp/data/ucod/united_states/Comparability_Ratio_tables.xls
"vbp/data/ucod/united_states/Underlying Cause of Death, 1999-2017_US_ICD10_113_SELECTED_CAUSES.txt"
"vbp/data/ucod/united_states/Underlying Cause of Death, 1999-2017_US_ICD10_CHAPTERS.txt"
"vbp/data/ucod/united_states/Underlying Cause of Death, 1999-2017_US_ICD10_MINIMALLY_GROUPED.txt"
"vbp/data/ucod/united_states/Underlying Cause of Death, 1999-2017_US_ICD10_SUB_CHAPTERS.txt"
vbp/data/ucod/united_states/comparable_data_since_1959.xlsx
vbp/data/ucod/united_states/comparable_ucod_estimates.xlsx
vbp/data/ucod/united_states/comparable_ucod_estimates_ratios_applied.xlsx
vbp/data/ucod/world/country_codes
vbp/data/ucod/world/pop
vbp/ucod/__init__.py
vbp/ucod/icd.py
vbp/ucod/united_states.py
vbp/ucod/world.py
vbp-0.3.6.dist-info/METADATA
vbp-0.3.6.dist-info/WHEEL
vbp-0.3.6.dist-info/entry_points.txt
vbp-0.3.6.dist-info/top_level.txt
vbp-0.3.6.dist-info/RECORD
