Metadata-Version: 2.1
Name: vbp
Version: 0.3.6
Summary: Value Based Prioritization
Home-page: https://github.com/freeradical13/ValueBasedPrioritization
Author: Free Radical
Author-email: freeradical@myplaceonline.com
License: UNKNOWN
Project-URL: Bug Reports, https://github.com/freeradical13/ValueBasedPrioritization/issues
Project-URL: Source, https://github.com/freeradical13/ValueBasedPrioritization
Keywords: value based prioritization
Platform: UNKNOWN
Classifier: Development Status :: 3 - Alpha
Classifier: Intended Audience :: Developers
Classifier: Topic :: Software Development :: Libraries
Classifier: License :: Public Domain
Classifier: Programming Language :: Python :: 3
Classifier: Operating System :: OS Independent
Requires-Python: >=3.5
Requires-Dist: numpy
Requires-Dist: pandas
Requires-Dist: matplotlib
Requires-Dist: statsmodels
Requires-Dist: scipy
Requires-Dist: fbprophet
